{"source_path": "dante-divine_comedy.txt", "text": "\nTranslanted by H. F. Cary [Preface and Chronlogy end this file]\n\n\nCopyright laws are changing all over the world, be sure to check\nthe copyright laws for your country before posting these files!!\n\nPlease take a look at the important information in this header.\nWe encourage you to keep this file on your own disk, keeping an\nelectronic path open for the next readers.  Do not remove this.\n\n\n**Welcome To The World of Free Plain Vanilla Electronic Texts**\n\n**Etexts Readable By Both Humans and By Computers, Since 1971**\n\n*These Etexts Prepared By Hundreds of Volunteers and Donations*\n\nInformation on contacting Project Gutenberg to get Etexts, and\nfurther information is included below.  We need your donations.\n\n\nThe Divine Comedy of Dante\n\nTranslanted by H. F. Cary\n\nAugust, 1997  [Etext #1008]\n[Date last updated: November 21. 2005]\n\n\n\n******This file should be named 1008.txt or 1008.zip**", "char_list": ["t", "r", "a", "n", "s", "l", "a", "n", "t", "e", "d", " ", "b", "y", " ", "h", ".", " ", "f", ".", " ", "c", "a", "r", "y", " ", "[", "p", "r", "e", "f", "a", "c", "e", " ", "a", "n", "d", " ", "c", "h", "r", "o", "n", "l", "o", "g", "y", " ", "e", "n", "d", " ", "t", "h", "i", "s", " ", "f", "i", "l", "e", "]", "c", "o", "p", "y", "r", "i", "g", "h", "t", " ", "l", "a", "w", "s", " ", "a", "r", "e", " ", "c", "h", "a", "n", "g", "i", "n", "g", " ", "a", "l", "l", " ", "o", "v", "e", "r", " ", "t", "h", "e", " ", "w", "o", "r", "l", "d", ",", " ", "b", "e", " ", "s", "u", "r", "e", " ", "t", "o", " ", "c", "h", "e", "c", "k", "t", "h", "e", " ", "c", "o", "p", "y", "r", "i", "g", "h", "t", " ", "l", "a", "w", "s", " ", "f", "o", "r", " ", "y", "o", "u", "r", " ", "c", "o", "u", "n", "t", "r", "y", " ", "b", "e", "f", "o", "r", "e", " ", "p", "o", "s", "t", "i", "n", "g", " ", "t", "h", "e", "s", "e", " ", "f", "i", "l", "e", "s", "!", "!", "p", "l", "e", "a", "s", "e", " ", "t", "a", "k", "e", " ", "a", " ", "l", "o", "o", "k", " ", "a", "t", " ", "t", "h", "e", " ", "i", "m", "p", "o", "r", "t", "a", "n", "t", " ", "i", "n", "f", "o", "r", "m", "a", "t", "i", "o", "n", " ", "i", "n", " ", "t", "h", "i", "s", " ", "h", "e", "a", "d", "e", "r", ".", "w", "e", " ", "e", "n", "c", "o", "u", "r", "a", "g", "e", " ", "y", "o", "u", " ", "t", "o", " ", "k", "e", "e", "p", " ", "t", "h", "i", "s", " ", "f", "i", "l", "e", " ", "o", "n", " ", "y", "o", "u", "r", " ", "o", "w", "n", " ", "d", "i", "s", "k", ",", " ", "k", "e", "e", "p", "i", "n", "g", " ", "a", "n", "e", "l", "e", "c", "t", "r", "o", "n", "i", "c", " ", "p", "a", "t", "h", " ", "o", "p", "e", "n", " ", "f", "o", "r", " ", "t", "h", "e", " ", "n", "e", "x", "t", " ", "r", "e", "a", "d", "e", "r", "s", ".", " ", " ", "d", "o", " ", "n", "o", "t", " ", "r", "e", "m", "o", "v", "e", " ", "t", "h", "i", "s", ".", "*", "*", "w", "e", "l", "c", "o", "m", "e", " ", "t", "o", " ", "t", "h", "e", " ", "w", "o", "r", "l", "d", " ", "o", "f", " ", "f", "r", "e", "e", " ", "p", "l", "a", "i", "n", " ", "v", "a", "n", "i", "l", "l", "a", " ", "e", "l", "e", "c", "t", "r", "o", "n", "i", "c", " ", "t", "e", "x", "t", "s", "*", "*", "*", "*", "e", "t", "e", "x", "t", "s", " ", "r", "e", "a", "d", "a", "b", "l", "e", " ", "b", "y", " ", "b", "o", "t", "h", " ", "h", "u", "m", "a", "n", "s", " ", "a", "n", "d", " ", "b", "y", " ", "c", "o", "m", "p", "u", "t", "e", "r", "s", ",", " ", "s", "i", "n", "c", "e", " ", "1", "9", "7", "1", "*", "*", "*", "t", "h", "e", "s", "e", " ", "e", "t", "e", "x", "t", "s", " ", "p", "r", "e", "p", "a", "r", "e", "d", " ", "b", "y", " ", "h", "u", "n", "d", "r", "e", "d", "s", " ", "o", "f", " ", "v", "o", "l", "u", "n", "t", "e", "e", "r", "s", " ", "a", "n", "d", " ", "d", "o", "n", "a", "t", "i", "o", "n", "s", "*", "i", "n", "f", "o", "r", "m", "a", "t", "i", "o", "n", " ", "o", "n", " ", "c", "o", "n", "t", "a", "c", "t", "i", "n", "g", " ", "p", "r", "o", "j", "e", "c", "t", " ", "g", "u", "t", "e", "n", "b", "e", "r", "g", " ", "t", "o", " ", "g", "e", "t", " ", "e", "t", "e", "x", "t", "s", ",", " ", "a", "n", "d", "f", "u", "r", "t", "h", "e", "r", " ", "i", "n", "f", "o", "r", "m", "a", "t", "i", "o", "n", " ", "i", "s", " ", "i", "n", "c", "l", "u", "d", "e", "d", " ", "b", "e", "l", "o", "w", ".", " ", " ", "w", "e", " ", "n", "e", "e", "d", " ", "y", "o", "u", "r", " ", "d", "o", "n", "a", "t", "i", "o", "n", "s", ".", "t", "h", "e", " ", "d", "i", "v", "i", "n", "e", " ", "c", "o", "m", "e", "d", "y", " ", "o", "f", " ", "d", "a", "n", "t", "e", "t", "r", "a", "n", "s", "l", "a", "n", "t", "e", "d", " ", "b", "y", " ", "h", ".", " ", "f", ".", " ", "c", "a", "r", "y", "a", "u", "g", "u", "s", "t", ",", " ", "1", "9", "9", "7", " ", " ", "[", "e", "t", "e", "x", "t", " ", "#", "1", "0", "0", "8", "]", "[", "d", "a", "t", "e", " ", "l", "a", "s", "t", " ", "u", "p", "d", "a", "t", "e", "d", ":", " ", "n", "o", "v", "e", "m", "b", "e", "r", " ", "2", "1", ".", " ", "2", "0", "0", "5", "]", "*", "*", "*", "*", "*", "*", "t", "h", "i", "s", " ", "f", "i", "l", "e", " ", "s", "h", "o", "u", "l", "d", " ", "b", "e", " ", "n", "a", "m", "e", "d", " ", "1", "0", "0", "8", ".", "t", "x", "t", " ", "o", "r", " ", "1", "0", "0", "8", ".", "z", "i", "p", "*", "*"], "word_list": ["Translanted", "by", "H.", "F.", "Cary", "[Preface", "and", "Chronlogy", "end", "this", "file]", "Copyright", "laws", "are", "changing", "all", "over", "the", "world,", "be", "sure", "to", "check", "the", "copyright", "laws", "for", "your", "country", "before", "posting", "these", "files!!", "Please", "take", "a", "look", "at", "the", "important", "information", "in", "this", "header.", "We", "encourage", "you", "to", "keep", "this", "file", "on", "your", "own", "disk,", "keeping", "an", "electronic", "path", "open", "for", "the", "next", "readers.", "Do", "not", "remove", "this.", "**Welcome", "To", "The", "World", "of", "Free", "Plain", "Vanilla", "Electronic", "Texts**", "**Etexts", "Readable", "By", "Both", "Humans", "and", "By", "Computers,", "Since", "1971**", "*These", "Etexts", "Prepared", "By", "Hundreds", "of", "Volunteers", "and", "Donations*", "Information", "on", "contacting", "Project", "Gutenberg", "to", "get", "Etexts,", "and", "further", "information", "is", "included", "below.", "We", "need", "your", "donations.", "The", "Divine", "Comedy", "of", "Dante", "Translanted", "by", "H.", "F.", "Cary", "August,", "1997", "[Etext", "#1008]", "[Date", "last", "updated:", "November", "21.", "2005]", "******This", "file", "should", "be", "named", "1008.txt", "or", "1008.zip**"], "word_pos": ["Translanted-VBN", "by-IN", "H.-NNP", "F.-NNP", "Cary-NNP", "[Preface-NN", "and-CC", "Chronlogy-NNP", "end-VBP", "this-DT", "file]-NN", "Copyright-NNP", "laws-NNS", "are-VBP", "changing-VBG", "all-DT", "over-IN", "the-DT", "world,-NN", "be-VB", "sure-JJ", "to-TO", "check-VB", "the-DT", "copyright-NN", "laws-NNS", "for-IN", "your-PRP$", "country-NN", "before-IN", "posting-VBG", "these-DT", "files!!-JJ", "Please-NNP", "take-VB", "a-DT", "look-NN", "at-IN", "the-DT", "important-JJ", "information-NN", "in-IN", "this-DT", "header.-NN", "We-PRP", "encourage-VBP", "you-PRP", "to-TO", "keep-VB", "this-DT", "file-NN", "on-IN", "your-PRP$", "own-JJ", "disk,-NN", "keeping-VBG", "an-DT", "electronic-JJ", "path-NN", "open-JJ", "for-IN", "the-DT", "next-JJ", "readers.-NN", "Do-NNP", "not-RB", "remove-VB", "this.-RB", "**Welcome-JJ", "To-TO", "The-DT", "World-NNP", "of-IN", "Free-NNP", "Plain-NNP", "Vanilla-NNP", "Electronic-NNP", "Texts**-NNP", "**Etexts-NNP", "Readable-NNP", "By-IN", "Both-NNP", "Humans-NNP", "and-CC", "By-IN", "Computers,-NNP", "Since-IN", "1971**-CD", "*These-JJ", "Etexts-NNP", "Prepared-NNP", "By-IN", "Hundreds-NNP", "of-IN", "Volunteers-NNP", "and-CC", "Donations*-NNP", "Information-NNP", "on-IN", "contacting-VBG", "Project-NNP", "Gutenberg-NNP", "to-TO", "get-VB", "Etexts,-NNP", "and-CC", "further-JJ", "information-NN", "is-VBZ", "included-VBN", "below.-IN", "We-PRP", "need-VBP", "your-PRP$", "donations.-NN", "The-DT", "Divine-NNP", "Comedy-NNP", "of-IN", "Dante-NNP", "Translanted-NNP", "by-IN", "H.-NNP", "F.-NNP", "Cary-NNP", "August,-NNP", "1997-CD", "[Etext-NNP", "#1008]-NNP", "[Date-NNP", "last-JJ", "updated:-JJ", "November-NNP", "21.-CD", "2005]-CD", "******This-NNS", "file-NN", "should-MD", "be-VB", "named-VBN", "1008.txt-CD", "or-CC", "1008.zip**-CD"]}